tau_fibrils_yolo/__init__.py
tau_fibrils_yolo/__main__.py
tau_fibrils_yolo/_version.py
tau_fibrils_yolo/boxes_utils.py
tau_fibrils_yolo/cli.py
tau_fibrils_yolo/napari.yaml
tau_fibrils_yolo/widget.py
tau_fibrils_yolo/sample/sample.tif
tau_fibrils_yolo-0.1.0.dist-info/licenses/LICENSE
tau_fibrils_yolo-0.1.0.dist-info/METADATA
tau_fibrils_yolo-0.1.0.dist-info/WHEEL
tau_fibrils_yolo-0.1.0.dist-info/entry_points.txt
tau_fibrils_yolo-0.1.0.dist-info/top_level.txt
tau_fibrils_yolo-0.1.0.dist-info/RECORD
