Metadata-Version: 2.4
Name: tau-fibrils-yolo
Version: 0.1.0
Summary: YoloV8 model for the detection of Tau fibrils in EM images.
Author-email: Mallory Wittwer <mallory.wittwer@epfl.ch>
License:                     GNU AFFERO GENERAL PUBLIC LICENSE
Project-URL: homepage, https://github.com/EPFL-Center-for-Imaging/tau_fibrils_yolo
Project-URL: repository, https://github.com/EPFL-Center-for-Imaging/tau_fibrils_yolo
Classifier: Development Status :: 2 - Pre-Alpha
Classifier: License :: OSI Approved :: BSD License
Classifier: Programming Language :: Python :: 3
Classifier: Programming Language :: Python :: 3.9
Classifier: Programming Language :: Python :: 3.10
Classifier: Programming Language :: Python :: 3.11
Classifier: Programming Language :: Python :: 3.12
Classifier: Programming Language :: Python :: 3.13
Classifier: Topic :: Scientific/Engineering :: Image Processing
Requires-Python: >=3.9
License-File: LICENSE
Requires-Dist: napari[all]>=0.4.16
Requires-Dist: qtpy
Requires-Dist: magicgui
Requires-Dist: numpy
Requires-Dist: pandas
Requires-Dist: tifffile
Requires-Dist: matplotlib
Requires-Dist: pooch==1.8.0
Requires-Dist: scikit-image
Requires-Dist: scikit-learn
Requires-Dist: ultralytics
Requires-Dist: opencv-contrib-python-headless
Requires-Dist: imaging-server-kit>=0.1.3
Requires-Dist: napari-serverkit>=0.0.9
Dynamic: license-file
